Workbook
Name aporte: App!$C$19
Name patrimonio: App!$C$22
Name qrd_anos: App!$C$20
Name qtd_anos: App!$C$20
Name rendimento_carteira: App!$D$15
Name salario: App!$D$14
Name sugestao: App!$D$16
Name tx_mensal: App!$C$21

Sheet App
A2: Clipes Investimentos
B13: Configurações
B14: Salário | D14: 5000
B15: Rendimento Carteira | D15: 0.01
B16: Sugestão de Investimento (30%) | D16: =D14*30% -> 1500
B18: Investimento Mensal
B19: Quanto investir por mês? | C19: 750
B20: Por Quantos anos? | C20: 5
A21: 2 | B21: Taxa de rendimento mensal? | C21: 0.01079
A22: 5 | B22: Patrimônio Acumulado? | C22: =FV(tx_mensal,qtd_anos*12,aporte)*(-1) -> 62832.685
A23: 10 | B23: Dividendos Mensais? | C23: =C22*$D$15 -> 628.32685
A24: 20
A25: 30 | B25: Cenários | D25: Dividendo
B26: Quanto em 2 anos? | C26: =FV($C$21,$A21*12,$C$19)*(-1) -> 20420.72 | D26: =C26*rendimento_carteira -> 204.2072
B27: Quanto em 5 anos? | C27: =FV($C$21,$A22*12,$C$19)*(-1) -> 62832.685 | D27: =C27*rendimento_carteira -> 628.32685
B28: Quanto em 10 anos? | C28: =FV($C$21,$A23*12,$C$19)*(-1) -> 182463.16 | D28: =C28*rendimento_carteira -> 1824.6316
B29: Quanto em 20 anos? | C29: =FV($C$21,$A24*12,$C$19)*(-1) -> 843898.8 | D29: =C29*rendimento_carteira -> 8438.988
B30: Quanto em 30 anos? | C30: =FV($C$21,$A25*12,$C$19)*(-1) -> 3241627.2 | D30: =C30*rendimento_carteira -> 32416.272
B33: Perfil | C33: Moderado
B34: Valor a ser investido por mês | C34: =aporte -> 750
B36: Tipo de FII | C36: Percentual sugerido | D36: Valores
B37: Papel | C37: =VLOOKUP($C$33&"-"&B37,Apoio!B:F,4,FALSE) -> 0.32 | D37: =C37*$C$34 -> 240
B38: Tijolo | C38: =VLOOKUP($C$33&"-"&B38,Apoio!B:F,4,FALSE) -> 0.3 | D38: =C38*$C$34 -> 225
B39: Híbridos | C39: =VLOOKUP($C$33&"-"&B39,Apoio!B:F,4,FALSE) -> 0.08 | D39: =C39*$C$34 -> 60
B40: FOFs | C40: =VLOOKUP($C$33&"-"&B40,Apoio!B:F,4,FALSE) -> 0.1 | D40: =C40*$C$34 -> 75
B41: Desenvolvimento | C41: =VLOOKUP($C$33&"-"&B41,Apoio!B:F,4,FALSE) -> 0.1 | D41: =C41*$C$34 -> 75
B42: Hotelarias | C42: =VLOOKUP($C$33&"-"&B42,Apoio!B:F,4,FALSE) -> 0.1 | D42: =C42*$C$34 -> 75
B43: Total | C43: 1 | D43: =SUM(D37:D42) -> 750

Sheet Apoio
L3: %
B4: Chave | C4: Perfil | D4: Tipo de FII | E4: % | K4: =B12 -> Moderado-Tijolo | L4: =VLOOKUP($K$4,$B:$F,4,FALSE) -> 0.3
B5: =C5&"-"&D5 -> Conservador-Papel | C5: Conservador | D5: Papel | E5: 0.3 | F5: 225
B6: =C6&"-"&D6 -> Conservador-Tijolo | C6: Conservador | D6: Tijolo | E6: 0.5 | F6: 375
B7: =C7&"-"&D7 -> Conservador-Híbridos | C7: Conservador | D7: Híbridos | E7: 0.1 | F7: 75
B8: =C8&"-"&D8 -> Conservador-FOFs | C8: Conservador | D8: FOFs | E8: 0.1 | F8: 75
B9: =C9&"-"&D9 -> Conservador-Desenvolvimento | C9: Conservador | D9: Desenvolvimento | E9: 0 | F9: 0
B10: =C10&"-"&D10 -> Conservador-Hotelarias | C10: Conservador | D10: Hotelarias | E10: 0 | F10: 0
B11: =C11&"-"&D11 -> Moderado-Papel | C11: Moderado | D11: Papel | E11: 0.32
B12: =C12&"-"&D12 -> Moderado-Tijolo | C12: Moderado | D12: Tijolo | E12: 0.3
B13: =C13&"-"&D13 -> Moderado-Híbridos | C13: Moderado | D13: Híbridos | E13: 0.08
B14: =C14&"-"&D14 -> Moderado-FOFs | C14: Moderado | D14: FOFs | E14: 0.1
B15: =C15&"-"&D15 -> Moderado-Desenvolvimento | C15: Moderado | D15: Desenvolvimento | E15: 0.1
B16: =C16&"-"&D16 -> Moderado-Hotelarias | C16: Moderado | D16: Hotelarias | E16: 0.1
B17: =C17&"-"&D17 -> Agressivo-Papel | C17: Agressivo | D17: Papel | E17: 0.5
B18: =C18&"-"&D18 -> Agressivo-Tijolo | C18: Agressivo | D18: Tijolo | E18: 0.2
B19: =C19&"-"&D19 -> Agressivo-Híbridos | C19: Agressivo | D19: Híbridos | E19: 0.05
B20: =C20&"-"&D20 -> Agressivo-FOFs | C20: Agressivo | D20: FOFs | E20: 0.05
B21: =C21&"-"&D21 -> Agressivo-Desenvolvimento | C21: Agressivo | D21: Desenvolvimento | E21: 0.1
B22: =C22&"-"&D22 -> Agressivo-Hotelarias | C22: Agressivo | D22: Hotelarias | E22: 0.1
